setup.py
releasetools/__init__.py
releasetools/common.py
releasetools.egg-info/PKG-INFO
releasetools.egg-info/SOURCES.txt
releasetools.egg-info/dependency_links.txt
releasetools.egg-info/entry_points.txt
releasetools.egg-info/requires.txt
releasetools.egg-info/top_level.txt
releasetools.egg-info/zip-safe
releasetools/tracker/__init__.py
releasetools/tracker/main.py
releasetools/tracker/sf_allura.py