Metadata-Version: 1.0
Name: releasetools
Version: 0.1
Summary: A set of tools and helper scripts to make managing a release process easier
Home-page: https://github.com/pedersen/releasetools
Author: Michael J. Pedersen
Author-email: m.pedersen@icelus.org
License: UNKNOWN
Platform: UNKNOWN
